{"adapter": "hi", "num_seeds": 1, "f1": 92.16325591208117}
{"adapter": "ka", "num_seeds": 1, "f1": 88.7042202221775}
{"adapter": "en", "num_seeds": 1, "f1": 88.58104286303195}
{"adapter": "vi", "num_seeds": 1, "f1": 88.27725050330744}
{"adapter": "hu", "num_seeds": 1, "f1": 88.18797994420423}
{"adapter": "id", "num_seeds": 1, "f1": 88.17426988053462}
{"adapter": "pt", "num_seeds": 1, "f1": 88.08905664715518}
{"adapter": "zh_yue", "num_seeds": 1, "f1": 87.81833208403008}
{"adapter": "am", "num_seeds": 1, "f1": 87.56499008990895}
{"adapter": "cs", "num_seeds": 1, "f1": 87.55083099710083}
{"adapter": "bn", "num_seeds": 1, "f1": 87.54324598122982}
{"adapter": "hy", "num_seeds": 1, "f1": 87.44795903718237}
{"adapter": "de", "num_seeds": 1, "f1": 87.15419958859604}
{"adapter": "ja", "num_seeds": 1, "f1": 86.90606567141238}
{"adapter": "tr", "num_seeds": 1, "f1": 86.83769202020105}
{"adapter": "jv", "num_seeds": 1, "f1": 86.7727913872017}
{"adapter": "zh", "num_seeds": 1, "f1": 86.72887506480042}
{"adapter": "eu", "num_seeds": 1, "f1": 86.43335929911619}
{"adapter": "es", "num_seeds": 1, "f1": 86.41887474522171}
{"adapter": "fr", "num_seeds": 1, "f1": 86.36555995845036}
{"adapter": "ko", "num_seeds": 1, "f1": 86.07950176841457}
{"adapter": "bh", "num_seeds": 1, "f1": 85.8842721427886}
{"adapter": "my", "num_seeds": 1, "f1": 85.75191041476427}
{"adapter": "ru", "num_seeds": 1, "f1": 85.71291258963072}
{"adapter": "ar", "num_seeds": 1, "f1": 85.66555844056299}
{"adapter": "fa", "num_seeds": 1, "f1": 85.48453568724422}
{"adapter": "la", "num_seeds": 1, "f1": 85.20286853811935}
{"adapter": "el", "num_seeds": 1, "f1": 84.93308500220809}
{"adapter": "lv", "num_seeds": 1, "f1": 84.64340786430225}
{"adapter": "fi", "num_seeds": 1, "f1": 83.67130166087293}
{"adapter": "bxr", "num_seeds": 1, "f1": 83.59161699673139}
{"adapter": "ht", "num_seeds": 1, "f1": 82.73993659333271}
{"adapter": "mi", "num_seeds": 1, "f1": 82.31609473175449}
{"adapter": "qu", "num_seeds": 1, "f1": 82.04913349838125}
{"adapter": "ilo", "num_seeds": 1, "f1": 82.02351127384851}
{"adapter": "cdo", "num_seeds": 1, "f1": 81.97734096948417}
{"adapter": "is", "num_seeds": 1, "f1": 81.67806412629601}
{"adapter": "et", "num_seeds": 1, "f1": 81.09145088568397}
{"adapter": "sw", "num_seeds": 1, "f1": 80.44936477733573}
{"adapter": "myv", "num_seeds": 1, "f1": 79.95191328880142}
{"adapter": "se", "num_seeds": 1, "f1": 79.92021660997679}
{"adapter": "tk", "num_seeds": 1, "f1": 79.87607190131793}
{"adapter": "kv", "num_seeds": 1, "f1": 78.97699200775006}
{"adapter": "gn", "num_seeds": 1, "f1": 77.17857592454511}
{"adapter": "xmf", "num_seeds": 1, "f1": 76.50648286499253}
{"adapter": "wo", "num_seeds": 1, "f1": 70.14491049645807}
{"adapter": "mhr", "num_seeds": 1, "f1": 69.89428347689899}
