{"adapter": "fi", "num_seeds": 1, "f1": 77.91294694481707}
{"adapter": "ka", "num_seeds": 1, "f1": 76.80251508356643}
{"adapter": "pt", "num_seeds": 1, "f1": 76.60601217188172}
{"adapter": "cs", "num_seeds": 1, "f1": 76.00646601493341}
{"adapter": "en", "num_seeds": 1, "f1": 75.8023071877773}
{"adapter": "zh_yue", "num_seeds": 1, "f1": 75.78626518265368}
{"adapter": "vi", "num_seeds": 1, "f1": 75.6295406969585}
{"adapter": "am", "num_seeds": 1, "f1": 75.38488872409292}
{"adapter": "id", "num_seeds": 1, "f1": 75.02098850061232}
{"adapter": "hu", "num_seeds": 1, "f1": 74.98787463527673}
{"adapter": "hy", "num_seeds": 1, "f1": 74.78856191261845}
{"adapter": "de", "num_seeds": 1, "f1": 74.74399581782959}
{"adapter": "bn", "num_seeds": 1, "f1": 74.32686383240913}
{"adapter": "tr", "num_seeds": 1, "f1": 74.2021706811687}
{"adapter": "ja", "num_seeds": 1, "f1": 74.14078435900396}
{"adapter": "fr", "num_seeds": 1, "f1": 73.94920552027095}
{"adapter": "el", "num_seeds": 1, "f1": 73.58654861255597}
{"adapter": "fa", "num_seeds": 1, "f1": 73.52481543352913}
{"adapter": "zh", "num_seeds": 1, "f1": 73.27699761972623}
{"adapter": "ru", "num_seeds": 1, "f1": 73.22562519723827}
{"adapter": "es", "num_seeds": 1, "f1": 73.05338581708592}
{"adapter": "my", "num_seeds": 1, "f1": 72.71124718762321}
{"adapter": "eu", "num_seeds": 1, "f1": 72.47275257014765}
{"adapter": "ar", "num_seeds": 1, "f1": 72.04610060561117}
{"adapter": "lv", "num_seeds": 1, "f1": 71.49714391720066}
{"adapter": "bh", "num_seeds": 1, "f1": 71.13520871845246}
{"adapter": "ko", "num_seeds": 1, "f1": 70.55391341831393}
{"adapter": "la", "num_seeds": 1, "f1": 69.85249280217361}
{"adapter": "bxr", "num_seeds": 1, "f1": 69.59020276304449}
{"adapter": "hi", "num_seeds": 1, "f1": 66.63830445544554}
{"adapter": "ht", "num_seeds": 1, "f1": 66.48135603777845}
{"adapter": "qu", "num_seeds": 1, "f1": 65.6329212955719}
{"adapter": "jv", "num_seeds": 1, "f1": 65.11264225439344}
{"adapter": "myv", "num_seeds": 1, "f1": 65.05977332712311}
{"adapter": "mhr", "num_seeds": 1, "f1": 64.64215644459608}
{"adapter": "cdo", "num_seeds": 1, "f1": 62.02636299820606}
{"adapter": "kv", "num_seeds": 1, "f1": 60.90355266838654}
{"adapter": "xmf", "num_seeds": 1, "f1": 59.43327682247518}
{"adapter": "se", "num_seeds": 1, "f1": 58.253327051263234}
{"adapter": "et", "num_seeds": 1, "f1": 58.21758809965607}
{"adapter": "is", "num_seeds": 1, "f1": 58.1546002310262}
{"adapter": "mi", "num_seeds": 1, "f1": 56.80729043915468}
{"adapter": "ilo", "num_seeds": 1, "f1": 56.77700416196663}
{"adapter": "gn", "num_seeds": 1, "f1": 54.29700414036303}
{"adapter": "sw", "num_seeds": 1, "f1": 50.501198693504534}
{"adapter": "tk", "num_seeds": 1, "f1": 49.10297096017988}
{"adapter": "wo", "num_seeds": 1, "f1": 37.83944156454231}
